{
 "meta": {
  "source": "서울 열린데이터광장 tbLnOpendataRtmsV (실거래)",
  "period": "2025~2026 접수분",
  "updated_note": "월간 자동 갱신"
 },
 "months": [
  "2025-02",
  "2025-03",
  "2025-04",
  "2025-05",
  "2025-06",
  "2025-07",
  "2025-08",
  "2025-09",
  "2025-10",
  "2025-11",
  "2025-12",
  "2026-01",
  "2026-02",
  "2026-03",
  "2026-04",
  "2026-05",
  "2026-06",
  "2026-07"
 ],
 "types": [
  "아파트",
  "연립다세대",
  "오피스텔",
  "단독다가구",
  "기타"
 ],
 "series": {
  "아파트": [
   6335,
   10459,
   5622,
   8473,
   12392,
   4426,
   4607,
   9011,
   9028,
   3520,
   4963,
   5624,
   6046,
   5746,
   8903,
   9102,
   4984,
   1619
  ],
  "연립다세대": [
   2132,
   3285,
   2674,
   3189,
   3959,
   2809,
   2740,
   3436,
   3525,
   2656,
   2981,
   3711,
   3023,
   3918,
   4423,
   4075,
   2905,
   580
  ],
  "오피스텔": [
   1300,
   1666,
   1151,
   1035,
   997,
   974,
   918,
   827,
   1226,
   1102,
   1122,
   1364,
   1062,
   1069,
   1342,
   1126,
   1055,
   265
  ],
  "단독다가구": [
   283,
   451,
   364,
   408,
   454,
   330,
   292,
   398,
   409,
   302,
   339,
   362,
   343,
   430,
   447,
   410,
   275,
   42
  ],
  "기타": [
   0,
   0,
   0,
   0,
   0,
   0,
   0,
   0,
   0,
   0,
   0,
   0,
   0,
   0,
   0,
   0,
   0,
   0
  ]
 },
 "total": [
  10050,
  15861,
  9811,
  13105,
  17802,
  8539,
  8557,
  13672,
  14188,
  7580,
  9405,
  11061,
  10474,
  11163,
  15115,
  14713,
  9219,
  2506
 ]
}